odoo/addons/extendable/README.rst
odoo/addons/extendable/__init__.py
odoo/addons/extendable/__manifest__.py
odoo/addons/extendable/registry.py
odoo/addons/extendable/i18n/extendable.pot
odoo/addons/extendable/i18n/it.po
odoo/addons/extendable/models/__init__.py
odoo/addons/extendable/models/extendable_registry_loader.py
odoo/addons/extendable/models/ir_http.py
odoo/addons/extendable/readme/CONTRIBUTORS.md
odoo/addons/extendable/readme/DESCRIPTION.md
odoo/addons/extendable/readme/ROADMAP.md
odoo/addons/extendable/readme/USAGE.md
odoo/addons/extendable/static/description/icon.png
odoo/addons/extendable/static/description/index.html
odoo/addons/extendable/tests/__init__.py
odoo/addons/extendable/tests/common.py
odoo_addon_extendable-18.0.1.0.2.1.dist-info/METADATA
odoo_addon_extendable-18.0.1.0.2.1.dist-info/WHEEL
odoo_addon_extendable-18.0.1.0.2.1.dist-info/top_level.txt
odoo_addon_extendable-18.0.1.0.2.1.dist-info/RECORD
