Metadata-Version: 2.1
Name: odoo-addon-extendable
Version: 18.0.1.0.2.1
Requires-Python: >=3.10
Requires-Dist: extendable>=0.0.4
Requires-Dist: odoo==18.0.*
Summary: Extendable classes registry loader for Odoo
Home-page: https://github.com/OCA/rest-framework
License: LGPL-3
Author: ACSONE SA/NV, Odoo Community Association (OCA)
Author-email: support@odoo-community.org
Classifier: Programming Language :: Python
Classifier: Framework :: Odoo
Classifier: Framework :: Odoo :: 18.0
Classifier: License :: OSI Approved :: GNU Lesser General Public License v3 (LGPLv3)
Classifier: Development Status :: 4 - Beta
